colbert_kit/__init__.py
colbert_kit/dataloader.py
colbert_kit/training.py
colbert_kit/utils.py
colbert_kit/choosing_negatives/__init__.py
colbert_kit/choosing_negatives/choosing_hard_negatives.py
colbert_kit/choosing_negatives/choosing_random_negatives.py
colbert_kit/embedding/__init__.py
colbert_kit/embedding/colbert_embedding.py
colbert_kit/embedding/sbert_embedding.py
colbert_kit/evaluating/__init__.py
colbert_kit/evaluating/ir_eval.py
colbert_kit/indexing/__init__.py
colbert_kit/indexing/bm25/__init__.py
colbert_kit/indexing/bm25/bm_25.py
colbert_kit/indexing/faiss/HNSW_faiss_index.py
colbert_kit/indexing/faiss/IVF_faiss_index.py
colbert_kit/indexing/faiss/__init__.py
colbert_kit/indexing/faiss/base_faiss_index.py
colbert_kit/indexing/faiss/flat_faiss_index.py
colbert_kit/reranking/__init__.py
colbert_kit/reranking/colbert_batch_reranker.py
colbert_kit/retrieving/__init__.py
colbert_kit/retrieving/bm25_search.py
colbert_kit/retrieving/colbert_search_faiss.py
colbert_kit/retrieving/faiss_search.py
colbert_kit-0.0.1.dist-info/licenses/LICENSE
colbert_kit-0.0.1.dist-info/METADATA
colbert_kit-0.0.1.dist-info/WHEEL
colbert_kit-0.0.1.dist-info/top_level.txt
colbert_kit-0.0.1.dist-info/RECORD
